margincropper/__init__.py
margincropper-1.0.1.dist-info/WHEEL
margincropper-1.0.1.dist-info/METADATA
margincropper-1.0.1.dist-info/RECORD
